freechat_sdk/__init__.py
freechat_sdk/api_client.py
freechat_sdk/api_response.py
freechat_sdk/configuration.py
freechat_sdk/exceptions.py
freechat_sdk/py.typed
freechat_sdk/rest.py
freechat_sdk/api/__init__.py
freechat_sdk/api/account_api.py
freechat_sdk/api/account_manager_for_admin_api.py
freechat_sdk/api/agent_api.py
freechat_sdk/api/ai_service_api.py
freechat_sdk/api/app_config_for_admin_api.py
freechat_sdk/api/app_meta_for_admin_api.py
freechat_sdk/api/character_api.py
freechat_sdk/api/chat_api.py
freechat_sdk/api/encryption_manager_for_admin_api.py
freechat_sdk/api/interactive_statistics_api.py
freechat_sdk/api/organization_api.py
freechat_sdk/api/plugin_api.py
freechat_sdk/api/prompt_api.py
freechat_sdk/api/prompt_task_api.py
freechat_sdk/api/rag_api.py
freechat_sdk/api/tag_manager_for_biz_admin_api.py
freechat_sdk/api/tts_service_api.py
freechat_sdk/models/__init__.py
freechat_sdk/models/agent_create_dto.py
freechat_sdk/models/agent_details_dto.py
freechat_sdk/models/agent_item_for_name_dto.py
freechat_sdk/models/agent_query_dto.py
freechat_sdk/models/agent_query_where.py
freechat_sdk/models/agent_summary_dto.py
freechat_sdk/models/agent_summary_stats_dto.py
freechat_sdk/models/agent_update_dto.py
freechat_sdk/models/ai_api_key_create_dto.py
freechat_sdk/models/ai_api_key_info_dto.py
freechat_sdk/models/ai_model_info_dto.py
freechat_sdk/models/api_token_info_dto.py
freechat_sdk/models/app_meta_dto.py
freechat_sdk/models/character_backend_details_dto.py
freechat_sdk/models/character_backend_dto.py
freechat_sdk/models/character_create_dto.py
freechat_sdk/models/character_details_dto.py
freechat_sdk/models/character_item_for_name_dto.py
freechat_sdk/models/character_query_dto.py
freechat_sdk/models/character_query_where.py
freechat_sdk/models/character_summary_dto.py
freechat_sdk/models/character_summary_stats_dto.py
freechat_sdk/models/character_update_dto.py
freechat_sdk/models/chat_content_dto.py
freechat_sdk/models/chat_context_dto.py
freechat_sdk-2.5.0.dist-info/METADATA
freechat_sdk-2.5.0.dist-info/WHEEL
freechat_sdk-2.5.0.dist-info/top_level.txt
freechat_sdk-2.5.0.dist-info/RECORD
